pyppl_runcmd.py
pyppl_runcmd-0.0.3.dist-info/entry_points.txt
pyppl_runcmd-0.0.3.dist-info/LICENSE
pyppl_runcmd-0.0.3.dist-info/WHEEL
pyppl_runcmd-0.0.3.dist-info/METADATA
pyppl_runcmd-0.0.3.dist-info/RECORD
