Metadata-Version: 2.1
Name: pyppl-runcmd
Version: 0.0.3
Summary: Allowing to run local command before and after each process for PyPPL
License: MIT
Author: pwwang
Author-email: pwwang@pwwang.com
Requires-Python: >=3.6,<4.0
Classifier: License :: OSI Approved :: MIT License
Classifier: Programming Language :: Python :: 3
Classifier: Programming Language :: Python :: 3.6
Classifier: Programming Language :: Python :: 3.7
Classifier: Programming Language :: Python :: 3.8
Requires-Dist: cmdy
Requires-Dist: pyppl (>=3.0.0,<4.0.0)
